FSM1.v
module FSM1(
	input clk,
	input rst_n,
	input in,
	output reg[3:0] out_data
);
	parameter s0 = 0, s1 = 1, s2 = 2 , s3 = 3;
	reg[2:0] state, next_state;

	always @(*)begin
		case(state)
			s0: next_state = in ? s1 : s0;
			s1: next_state = in ? s1 : s2;
			s2: next_state = in ? s3 : s2;
			s3: next_state = in ? s3 : s0;
			default next_state = s0;
		endcase
	end
	
	always @(posedge clk or negedge rst_n)begin
		if(!rst_n)begin
			state <= s0;
		end else begin
			state <= next_state;
		end
	end

	always @(*)begin
		case(state)
			s0: out_data <= 4'h0;
			s1: out_data <= 4'h1;
			s2: out_data <= 4'h8;
			s3: out_data <= 4'hf;
			default: out_data <= 4'h0;
		endcase
	end

endmodule

FSM_tb.v
`timescale 1ns / 1ps

module FSM_tb;


	reg clk;
	reg rst_n;
	reg in;


	wire [3:0] out_data;


	FSM1 FSM(
		clk,
		rst_n,
		in,
		out_data
	);

	initial begin
		clk = 0;
		forever #10 clk = ~clk;
	end

	initial begin
		$dumpfile("FSM1_wave.vcd");
		$dumpvars(0, FSM_tb);
	end

	initial begin

		rst_n = 0;
		in = 0;
		#25;
		rst_n = 1;
	
		#20;in = 1;

		#20;in = 0;

		#20;in = 1;

		#20;in = 0;
		#40;

		$display("FSM1 test finish");
		$finish;
	end


endmodule

FSM1_wave.vcd
$date
	Sat May 23 14:40:47 2026
$end
$version
	Icarus Verilog
$end
$timescale
	1ps
$end
$scope module FSM_tb $end
$var wire 4 ! out_data [3:0] $end
$var reg 1 " clk $end
$var reg 1 # in $end
$var reg 1 $ rst_n $end
$scope module FSM $end
$var wire 1 " clk $end
$var wire 1 # in $end
$var wire 1 $ rst_n $end
$var reg 3 % next_state [2:0] $end
$var reg 4 & out_data [3:0] $end
$var reg 3 ' state [2:0] $end
$upscope $end
$upscope $end
$enddefinitions $end
#0
$dumpvars
b0 '
b0 &
b0 %
0$
0#
0"
b0 !
$end
#10000
1"
#20000
0"
#25000
1$
#30000
1"
#40000
0"
#45000
b1 %
1#
#50000
b1 !
b1 &
b1 '
1"
#60000
0"
#65000
b10 %
0#
#70000
b1000 !
b1000 &
b10 '
1"
#80000
0"
#85000
b11 %
1#
#90000
b1111 !
b1111 &
b11 '
1"
#100000
0"
#105000
b0 %
0#
#110000
b0 !
b0 &
b0 '
1"
